win32/__init__.py
win32/gui.pyd
win32/mfc140u.dll
win32/mfcm140u.dll
win32/ole.pyd
win32/ui.pyd
win32/distutils/__init__.py
win32/distutils/gui.py
win32/distutils/headers/win32gui.zip
win32gui-221.5.dist-info/DESCRIPTION.rst
win32gui-221.5.dist-info/METADATA
win32gui-221.5.dist-info/RECORD
win32gui-221.5.dist-info/WHEEL
win32gui-221.5.dist-info/metadata.json
win32gui-221.5.dist-info/top_level.txt
