Metadata-Version: 1.0
Name: win32gui
Version: 221.5
Summary: Python for Window Extensions
Home-page: http://sourceforge.net/projects/pywin32/
Author: Mark Hammond (et al)
Author-email: mhammond@users.sourceforge.net
License: PSF
Platform: UNKNOWN
